odoo/addons/ssi_assurance_report_custom_information/README.rst
odoo/addons/ssi_assurance_report_custom_information/__init__.py
odoo/addons/ssi_assurance_report_custom_information/__manifest__.py
odoo/addons/ssi_assurance_report_custom_information/models/__init__.py
odoo/addons/ssi_assurance_report_custom_information/models/accountant_assurance_report.py
odoo/addons/ssi_assurance_report_custom_information/static/description/icon.png
odoo14_addon_ssi_assurance_report_custom_information-14.0.1.2.0.dist-info/METADATA
odoo14_addon_ssi_assurance_report_custom_information-14.0.1.2.0.dist-info/WHEEL
odoo14_addon_ssi_assurance_report_custom_information-14.0.1.2.0.dist-info/top_level.txt
odoo14_addon_ssi_assurance_report_custom_information-14.0.1.2.0.dist-info/RECORD
